lightworks_remote/__init__.py
lightworks_remote/__main__.py
lightworks_remote/__version.py
lightworks_remote/py.typed
lightworks_remote/http/__init__.py
lightworks_remote/http/artemis_interface.py
lightworks_remote/http/artemis_job_details.py
lightworks_remote/http/artemis_qpu_details.py
lightworks_remote/http/interface.py
lightworks_remote/http/job_details.py
lightworks_remote/http/qpu_details.py
lightworks_remote/http/status.py
lightworks_remote/payloads/__init__.py
lightworks_remote/payloads/payload.py
lightworks_remote/remote/__init__.py
lightworks_remote/remote/batch_job.py
lightworks_remote/remote/job.py
lightworks_remote/remote/job_management.py
lightworks_remote/remote/qpu.py
lightworks_remote/remote/sampler_compiler.py
lightworks_remote/remote/system_management.py
lightworks_remote/results/__init__.py
lightworks_remote/results/qpu_result.py
lightworks_remote/token/__init__.py
lightworks_remote/token/_token.py
lightworks_remote/utils/__init__.py
lightworks_remote/utils/configuration.py
lightworks_remote/utils/conversion.py
lightworks_remote/utils/exceptions.py
lightworks_remote/utils/file_management.py
lightworks_remote/utils/serialization.py
lightworks_remote-1.2.1.dist-info/licenses/LICENSE
lightworks_remote-1.2.1.dist-info/METADATA
lightworks_remote-1.2.1.dist-info/WHEEL
lightworks_remote-1.2.1.dist-info/entry_points.txt
lightworks_remote-1.2.1.dist-info/top_level.txt
lightworks_remote-1.2.1.dist-info/RECORD
