Metadata-Version: 2.4
Name: lightworks_remote
Version: 1.2.1
Summary: Remote job submission extension to lightworks.
Author: Aegiq Ltd.
License: Apache 2.0
Classifier: License :: OSI Approved :: Apache Software License
Classifier: Natural Language :: English
Classifier: Programming Language :: Python
Classifier: Programming Language :: Python :: 3.10
Classifier: Programming Language :: Python :: 3.11
Classifier: Programming Language :: Python :: 3.12
Classifier: Programming Language :: Python :: 3.13
Classifier: Programming Language :: Python :: 3.14
Classifier: Operating System :: OS Independent
Requires-Python: >=3.10
License-File: LICENSE
Requires-Dist: lightworks>=2.3.2
Requires-Dist: requests>=2.32.3
Requires-Dist: pandas
Requires-Dist: multimethod>=1.11.2
Dynamic: author
Dynamic: classifier
Dynamic: license
Dynamic: license-file
Dynamic: requires-dist
Dynamic: requires-python
Dynamic: summary
